{
  "name": "test_db-connector-1",
  "config": {
    "topic.prefix": "test_db",
    "connector.class": "io.debezium.connector.postgresql.PostgresConnector",
    "tasks.max": "1",
    "database.hostname": "postgres",
    "database.port": "5432",
    "database.user": "postgres",
    "database.password": "test",
    "database.server.id": "184054",
    "database.dbname": "test_db",
    "database.server.name": "dbserver1",
    "table.exclude.list": "public.users",
    "schema.history.kafka.bootstrap.servers": "kafka:9092",
    "schema.history.kafka.topic": "schema-changes.test_db",
    "transforms": "route",
    "transforms.route.type": "org.apache.kafka.connect.transforms.RegexRouter",
    "transforms.route.regex": "([^.]+)\\.([^.]+)\\.([^.]+)",
    "transforms.route.replacement": "$3"
  }
}
